s3verless/__init__.py
s3verless/cli.py
s3verless/auth/models.py
s3verless/auth/service.py
s3verless/core/base.py
s3verless/core/client.py
s3verless/core/exceptions.py
s3verless/core/query.py
s3verless/core/registry.py
s3verless/core/service.py
s3verless/core/settings.py
s3verless/fastapi/__init__.py
s3verless/fastapi/admin.py
s3verless/fastapi/app.py
s3verless/fastapi/auth.py
s3verless/fastapi/dependencies.py
s3verless/fastapi/router_generator.py
s3verless-0.1.1.dist-info/METADATA
s3verless-0.1.1.dist-info/WHEEL
s3verless-0.1.1.dist-info/entry_points.txt
s3verless-0.1.1.dist-info/licenses/LICENSE
s3verless-0.1.1.dist-info/RECORD
