Metadata-Version: 2.4
Name: s3verless
Version: 0.1.1
Summary: A framework for building serverless applications using S3 as a backend
Project-URL: Homepage, https://github.com/alexjacobs08/s3verless
Project-URL: Repository, https://github.com/alexjacobs08/s3verless
Project-URL: Documentation, https://s3verless.readthedocs.io
Project-URL: Issues, https://github.com/alexjacobs08/s3verless/issues
Author-email: S3verless Contributors <alex.jacobs08+s3verless@gmail.com>
License: MIT
License-File: LICENSE
Keywords: aws,backend,fastapi,s3,serverless
Classifier: Development Status :: 3 - Alpha
Classifier: Framework :: FastAPI
Classifier: Intended Audience :: Developers
Classifier: License :: OSI Approved :: MIT License
Classifier: Operating System :: OS Independent
Classifier: Programming Language :: Python :: 3
Classifier: Programming Language :: Python :: 3.9
Classifier: Programming Language :: Python :: 3.10
Classifier: Programming Language :: Python :: 3.11
Classifier: Programming Language :: Python :: 3.12
Classifier: Topic :: Internet :: WWW/HTTP :: HTTP Servers
Classifier: Topic :: Software Development :: Libraries :: Python Modules
Requires-Python: >=3.9
Requires-Dist: aiobotocore>=2.15.0
Requires-Dist: bcrypt<5.0.0,>=4.0.0
Requires-Dist: botocore>=1.35.0
Requires-Dist: click>=8.1.7
Requires-Dist: fastapi>=0.115.0
Requires-Dist: passlib[bcrypt]>=1.7.4
Requires-Dist: pydantic-settings>=2.6.0
Requires-Dist: pydantic[email]>=2.9.0
Requires-Dist: python-jose[cryptography]>=3.3.0
Requires-Dist: python-multipart>=0.0.12
Provides-Extra: dev
Requires-Dist: httpx>=0.27.0; extra == 'dev'
Requires-Dist: moto[s3]>=5.0.18; extra == 'dev'
Requires-Dist: mypy>=1.13.0; extra == 'dev'
Requires-Dist: pytest-asyncio>=0.24.0; extra == 'dev'
Requires-Dist: pytest-cov>=6.0.0; extra == 'dev'
Requires-Dist: pytest>=8.3.0; extra == 'dev'
Requires-Dist: ruff>=0.7.0; extra == 'dev'
